fixed_income/__init__.py
fixed_income/bond.py
fixed_income/risk.py
fixed_income-0.1.1.dist-info/licenses/LICENSE
fixed_income-0.1.1.dist-info/METADATA
fixed_income-0.1.1.dist-info/WHEEL
fixed_income-0.1.1.dist-info/top_level.txt
fixed_income-0.1.1.dist-info/RECORD
