Metadata-Version: 2.4
Name: fixed-income
Version: 0.1.1
Summary: Python library for analysis of fixed income instruments.
Author: Siddharth Kulkarni
License-Expression: MIT
Project-URL: Homepage, https://github.com/siddharthskulkarni/fixed-income
Project-URL: Issues, https://github.com/siddharthskulkarni/fixed-income/issues
Classifier: Intended Audience :: Science/Research
Classifier: Intended Audience :: Developers
Classifier: Programming Language :: C
Classifier: Programming Language :: Python
Classifier: Programming Language :: Python :: 3
Classifier: Programming Language :: Python :: 3.11
Classifier: Programming Language :: Python :: 3.12
Classifier: Programming Language :: Python :: 3.13
Classifier: Programming Language :: Python :: 3 :: Only
Classifier: Programming Language :: Python :: Implementation :: CPython
Classifier: Topic :: Scientific/Engineering
Classifier: Operating System :: Microsoft :: Windows
Classifier: Operating System :: POSIX
Classifier: Operating System :: Unix
Classifier: Operating System :: MacOS
Requires-Python: >=3.9
License-File: LICENSE
Dynamic: license-file
